WtfPy/UsageMonitor.py
WtfPy/WtfPy.py
WtfPy/__init__.py
WtfPy/__main__.py
WtfPy-0.0.2.dist-info/LICENSE
WtfPy-0.0.2.dist-info/METADATA
WtfPy-0.0.2.dist-info/WHEEL
WtfPy-0.0.2.dist-info/top_level.txt
WtfPy-0.0.2.dist-info/RECORD
