Metadata-Version: 2.1
Name: WtfPy
Version: 0.0.2
Summary: A basic module to work with memory addresses and references.
Home-page: https://github.com/Zyycyx/wtfpy
Author: Zyycyx
Author-email: peterschmidt5575@gmail.com
License: UNKNOWN
Platform: UNKNOWN
Classifier: Programming Language :: Python :: 3.8
Classifier: License :: OSI Approved :: MIT License
Classifier: Operating System :: OS Independent
Requires-Python: >=3.8
License-File: LICENSE
Requires-Dist: sys
